psychom_scanner
