Metadata-Version: 2.1
Name: psychom-scanner
Version: 0.1.1
Summary: psychom scanner is a python library which helps in security scanner creation
Home-page: UNKNOWN
Author: killercd
Author-email: killercd@gmail.com
License: UNKNOWN
Platform: UNKNOWN
